docspec/__init__.py
docspec/__main__.py
docspec/py.typed
docspec-2.2.0.dist-info/METADATA
docspec-2.2.0.dist-info/WHEEL
docspec-2.2.0.dist-info/entry_points.txt
docspec-2.2.0.dist-info/RECORD
