Metadata-Version: 2.1
Name: docspec
Version: 2.2.0
Summary: Docspec is a JSON object specification for representing API documentation of programming languages.
Home-page: https://github.com/NiklasRosenstein/docspec/
License: MIT
Author: Niklas Rosenstein
Author-email: rosensteinniklas@gmail.com
Requires-Python: >=3.7,<4.0
Classifier: License :: OSI Approved :: MIT License
Classifier: Programming Language :: Python :: 3
Classifier: Programming Language :: Python :: 3.7
Classifier: Programming Language :: Python :: 3.8
Classifier: Programming Language :: Python :: 3.9
Classifier: Programming Language :: Python :: 3.10
Classifier: Programming Language :: Python :: 3.11
Requires-Dist: Deprecated (>=1.2.12,<2.0.0)
Requires-Dist: databind-core (>=4.2.6,<5.0.0)
Requires-Dist: databind-json (>=4.2.6,<5.0.0)
